shigella_typing/__init__.py
shigella_typing/example.py
shigella_typing/parse_shigatype.py
shigella_typing/data/example_data.csv
shigella_typing-0.2.dev0.dist-info/METADATA
shigella_typing-0.2.dev0.dist-info/WHEEL
shigella_typing-0.2.dev0.dist-info/entry_points.txt
shigella_typing-0.2.dev0.dist-info/top_level.txt
shigella_typing-0.2.dev0.dist-info/RECORD
